MANIFEST.in
README.rst
setup.py
django_thwterm.egg-info/PKG-INFO
django_thwterm.egg-info/SOURCES.txt
django_thwterm.egg-info/dependency_links.txt
django_thwterm.egg-info/top_level.txt
thwterm/__init__.py
thwterm/apps.py
thwterm/thvisual.py
thwterm/urls.py
thwterm/views.py
thwterm/migrations/__init__.py
thwterm/static/css/app.aa8d09ded6395f7ff3291730fcd693cd.css
thwterm/static/css/app.aa8d09ded6395f7ff3291730fcd693cd.css.map
thwterm/static/fonts/element-icons.535877f.woff
thwterm/static/fonts/element-icons.732389d.ttf
thwterm/static/img/close_thwth56453.7541667.png
thwterm/static/img/font_thwth56453.2aa4a1a.png
thwterm/static/img/new_thwth56453.746b363.png
thwterm/static/img/set_thwth56453.61b0f37.png
thwterm/static/img/start_thwth56453.3ee57c3.png
thwterm/static/img/theme_thwth56453.5e5eb69.png
thwterm/static/js/app.3503a8793db9d3a5d689.js
thwterm/static/js/app.3503a8793db9d3a5d689.js.map
thwterm/static/js/manifest.2ae2e69a05c33dfc65f8.js
thwterm/static/js/manifest.2ae2e69a05c33dfc65f8.js.map
thwterm/static/js/vendor.f7b631c0f849bf69b770.js
thwterm/static/js/vendor.f7b631c0f849bf69b770.js.map
thwterm/templates/thwterm.html